jl95/pytools/envlib/vars/java/__init__.py
jl95terceira/pytools/envlib/vars/java/__init__.py
jl95terceira_pytools_env_java-0.2.8.dist-info/METADATA
jl95terceira_pytools_env_java-0.2.8.dist-info/WHEEL
jl95terceira_pytools_env_java-0.2.8.dist-info/RECORD
